wpymigrator/__init__.py
wpymigrator/__main__.py
wpymigrator-0.1.2.dist-info/entry_points.txt
wpymigrator-0.1.2.dist-info/LICENSE
wpymigrator-0.1.2.dist-info/WHEEL
wpymigrator-0.1.2.dist-info/METADATA
wpymigrator-0.1.2.dist-info/RECORD
